{
    "data": [
    {
        "id": 0,
        "name": "Create proper ToDo App",
        "description": "And don't forget to include MUI components!",
        "completed": true,
        "data": null,
        "IconId": 0,
        "tagId": 0
    },
    {
        "id": 1,
        "name": "Do some mindfulness meditation practice",
        "description": "Lorem ipsum and so on...",
        "completed": false,
        "data": null,
        "IconId": 4,
        "tagId": 1
    },
    {
        "id": 2,
        "name": "Vacuum the room",
        "description": null,
        "completed": false,
        "data": null,
        "IconId": 3,
        "tagId": 2
    }
]
}




